hydra_plugins/__init__.py
hydra_plugins/meta_blocks_searchpath_plugin/__init__.py
hydra_plugins/meta_blocks_searchpath_plugin/meta_blocks_searchpath_plugin.py
meta_blocks/__init__.py
meta_blocks/common.py
meta_blocks/version.py
meta_blocks/adaptation/__init__.py
meta_blocks/adaptation/base.py
meta_blocks/adaptation/maml.py
meta_blocks/adaptation/maml_utils.py
meta_blocks/adaptation/proto.py
meta_blocks/adaptation/proto_utils.py
meta_blocks/adaptation/reptile.py
meta_blocks/conf/__init__.py
meta_blocks/conf/config.yaml
meta_blocks/conf/hydra/job_logging/meta_blocks_log.yaml
meta_blocks/conf/meta_blocks/adaptation/classic_supervised/miniimagenet/fomaml.yaml
meta_blocks/conf/meta_blocks/adaptation/classic_supervised/miniimagenet/maml.yaml
meta_blocks/conf/meta_blocks/adaptation/classic_supervised/miniimagenet/proto.yaml
meta_blocks/conf/meta_blocks/adaptation/classic_supervised/miniimagenet/reptile.yaml
meta_blocks/conf/meta_blocks/adaptation/classic_supervised/omniglot/fomaml.yaml
meta_blocks/conf/meta_blocks/adaptation/classic_supervised/omniglot/maml.yaml
meta_blocks/conf/meta_blocks/adaptation/classic_supervised/omniglot/proto.yaml
meta_blocks/conf/meta_blocks/adaptation/classic_supervised/omniglot/reptile.yaml
meta_blocks/conf/meta_blocks/adaptation/self_supervised/miniimagenet/fomaml.yaml
meta_blocks/conf/meta_blocks/adaptation/self_supervised/miniimagenet/maml.yaml
meta_blocks/conf/meta_blocks/adaptation/self_supervised/miniimagenet/proto.yaml
meta_blocks/conf/meta_blocks/adaptation/self_supervised/miniimagenet/reptile.yaml
meta_blocks/conf/meta_blocks/adaptation/self_supervised/omniglot/fomaml.yaml
meta_blocks/conf/meta_blocks/adaptation/self_supervised/omniglot/maml.yaml
meta_blocks/conf/meta_blocks/adaptation/self_supervised/omniglot/proto.yaml
meta_blocks/conf/meta_blocks/adaptation/self_supervised/omniglot/reptile.yaml
meta_blocks/conf/meta_blocks/benchmark/classic_supervised/miniimagenet/20way1shot.yaml
meta_blocks-0.1a1.post1.dist-info/LICENSE
meta_blocks-0.1a1.post1.dist-info/METADATA
meta_blocks-0.1a1.post1.dist-info/WHEEL
meta_blocks-0.1a1.post1.dist-info/top_level.txt
meta_blocks-0.1a1.post1.dist-info/RECORD
