Metadata-Version: 2.1
Name: meta-blocks
Version: 0.1a1.post1
Summary: A modular toolbox for accelerating meta-learning research :rocket:
Home-page: https://github.com/alshedivat/meta-blocks
Author: Maruan Al-Shedivat
Author-email: alshedivat@cs.cmu.edu
Maintainer: Maruan Al-Shedivat, Yue Zhao
Maintainer-email: alshedivat@cs.cmu.edu, zhaoy@cmu.edu
License: BSD-3
Keywords: learning-to-learn,machine learning,deep learning,meta-learning,benchmark,toolbox,tensorflow,keras,python
Platform: UNKNOWN
Classifier: Development Status :: 3 - Alpha
Classifier: Intended Audience :: Education
Classifier: Intended Audience :: Science/Research
Classifier: Intended Audience :: Developers
Classifier: Intended Audience :: Information Technology
Classifier: License :: OSI Approved :: BSD License
Classifier: Programming Language :: Python :: 3
Classifier: Programming Language :: Python :: 3.6
Classifier: Programming Language :: Python :: 3.7
Classifier: Programming Language :: Python :: 3.8
Requires-Dist: albumentations
Requires-Dist: hydra-core (<1.0,>=0.11)
Requires-Dist: hydra-colorlog
Requires-Dist: numpy
Requires-Dist: omegaconf (<2.0,>=1.4)
Requires-Dist: Pillow
Requires-Dist: scipy
Requires-Dist: scikit-learn
Requires-Dist: tensorflow (==2.2.0rc3)
